realfastapi/__init__.py
realfastapi/cli.py
realfastapi/core.py
realfastapi/testing.py
realfastapi/auth/jwt.py
realfastapi/auth/routes.py
realfastapi/auth/security.py
realfastapi/crud/__init__.py
realfastapi/crud/base.py
realfastapi/crud/filters.py
realfastapi/crud/routes.py
realfastapi/database/__init__.py
realfastapi/database/base.py
realfastapi/database/session.py
realfastapi/schemas/__init__.py
realfastapi/schemas/token.py
realfastapi/schemas/user.py
realfastapi-0.1.0.dist-info/METADATA
realfastapi-0.1.0.dist-info/WHEEL
realfastapi-0.1.0.dist-info/licenses/LICENSE
realfastapi-0.1.0.dist-info/RECORD
