Metadata-Version: 2.4
Name: realfastapi
Version: 0.1.0
Summary: A production-ready wrapper application framework for FastAPI
Project-URL: Homepage, https://github.com/Jillou35/RealFastAPI
Project-URL: Repository, https://github.com/Jillou35/RealFastAPI
Project-URL: Issues, https://github.com/Jillou35/RealFastAPI/issues
Author-email: Jillian Strenk <jillian.strenk@posteo.net>
License-Expression: MIT
License-File: LICENSE
Classifier: Development Status :: 3 - Alpha
Classifier: Framework :: FastAPI
Classifier: Intended Audience :: Developers
Classifier: License :: OSI Approved :: MIT License
Classifier: Programming Language :: Python :: 3
Classifier: Programming Language :: Python :: 3.10
Classifier: Programming Language :: Python :: 3.11
Classifier: Programming Language :: Python :: 3.12
Classifier: Programming Language :: Python :: 3.13
Classifier: Topic :: Internet :: WWW/HTTP :: WSGI :: Application
Requires-Python: >=3.10
Requires-Dist: aiosqlite>=0.22.1
Requires-Dist: fastapi>=0.100.0
Requires-Dist: passlib[bcrypt]>=1.7.4
Requires-Dist: pydantic-settings>=2.0.0
Requires-Dist: pydantic>=2.0.0
Requires-Dist: pydantic[email]>=2.0.0
Requires-Dist: pyjwt>=2.0.0
Requires-Dist: python-multipart>=0.0.21
Requires-Dist: sqlalchemy>=2.0.0
Requires-Dist: uvicorn[standard]>=0.20.0
Provides-Extra: dev
Requires-Dist: black>=23.0.0; extra == 'dev'
Requires-Dist: httpx>=0.25.0; extra == 'dev'
Requires-Dist: isort>=5.0.0; extra == 'dev'
Requires-Dist: mypy>=1.0.0; extra == 'dev'
Requires-Dist: pytest-asyncio>=0.21.0; extra == 'dev'
Requires-Dist: pytest-cov>=4.0.0; extra == 'dev'
Requires-Dist: pytest>=7.0.0; extra == 'dev'
